decision_tree_writer/BaseDecisionTree.py
decision_tree_writer/CorrelatedDataComparer.py
decision_tree_writer/DataCleaner.py
decision_tree_writer/TreeWriter.py
decision_tree_writer/UncomparableDataSetItemsException.py
decision_tree_writer/__init__.py
decision_tree_writer-0.5.1.dist-info/LICENCE
decision_tree_writer-0.5.1.dist-info/METADATA
decision_tree_writer-0.5.1.dist-info/WHEEL
decision_tree_writer-0.5.1.dist-info/license.svg
decision_tree_writer-0.5.1.dist-info/top_level.txt
decision_tree_writer-0.5.1.dist-info/RECORD
