Metadata-Version: 2.1
Name: decision-tree-writer
Version: 0.5.1
Summary: Scaffolds out code for decision tree models that can learn to find relationships between multiple attributes of objects.
Home-page: https://github.com/AndreBacic/DecisionTreeWriter
Author: Andre Bacic
Author-email: andre9050@yahoo.com
Project-URL: Bug Tracker, https://github.com/AndreBacic/DecisionTreeWriter/issues
Classifier: Programming Language :: Python :: 3
Classifier: License :: OSI Approved :: MIT License
Classifier: Operating System :: OS Independent
Requires-Python: >=3.7
License-File: LICENCE
License-File: license.svg
